{
  "animals": [
    {
      "species" : "DOG",
      "data": {
        "race": "Golden Retriever",
        "identifier":  1,
        "linkedUser": 1,
        "name": "Toby",
        "age": 40,
        "weight": 80.03,
        "description": "Soy bueno :)",
        "img": "images/dogs/goldenRetriever1.jpg"
      }
    },
    {
      "species" : "CAT",
      "data": {
        "race": "Persian",
        "identifier":  2,
        "linkedUser": 1,
        "name": "Amancio",
        "age": 10,
        "weight": 140.03,
        "description": "jeje",
        "img": "images/cats/persian.jpg"
      }
    },
    {
      "species" : "DOG",
      "data": {
        "race": "Golden Retriever",
        "identifier":  3,
        "linkedUser": 1,
        "name": "Marcelino",
        "age": 40,
        "weight": 80.03,
        "description": "Soy bueno :)",
        "img": "images/dogs/goldenRetriever2.jpg"
      }
    },
    {
      "species" : "CAT",
      "data": {
        "race": "Abisinio",
        "identifier":  4,
        "linkedUser": 2,
        "name": "Gato",
        "age": 40,
        "weight": 80.03,
        "description": "Soy bueno :)",
        "img": "images/cats/abisinio.jpg"
      }
    }
  ]
}